mockerena/__init__.py
mockerena/app.py
mockerena/errors.py
mockerena/format.py
mockerena/generate.py
mockerena/providers.py
mockerena/settings.py
mockerena-1.3.1.dist-info/LICENSE.txt
mockerena-1.3.1.dist-info/METADATA
mockerena-1.3.1.dist-info/WHEEL
mockerena-1.3.1.dist-info/top_level.txt
mockerena-1.3.1.dist-info/RECORD
