Metadata-Version: 2.1
Name: mockerena
Version: 1.3.1
Summary: Self-hosting data mocking service
Home-page: https://github.com/FanThreeSixty/mockerena
Author: Michael Holtzscher
Author-email: mholtzscher@fanthreesixty.com
Maintainer: Michael Holtzscher
Maintainer-email: mholtzscher@fanthreesixty.com
License: MIT
Project-URL: Home, https://github.com/FanThreeSixty/mockerena
Project-URL: Tracker, https://github.com/FanThreeSixty/mockerena/issues
Keywords: flask data mock test api
Platform: UNKNOWN
Classifier: Development Status :: 5 - Production/Stable
Classifier: Framework :: Flask
Classifier: Intended Audience :: Developers
Classifier: Natural Language :: English
Classifier: Operating System :: MacOS :: MacOS X
Classifier: Operating System :: POSIX
Classifier: Operating System :: Microsoft :: Windows
Classifier: Programming Language :: Python :: 3.6
Classifier: Programming Language :: Python :: 3.7
Classifier: Programming Language :: Python :: 3.8
Classifier: Programming Language :: Python :: Implementation :: CPython
Classifier: Topic :: Software Development :: Quality Assurance
Classifier: Topic :: Software Development :: Testing
Classifier: Topic :: Software Development :: Testing :: Mocking
Requires-Python: >=3.6
Requires-Dist: dnspython (>=1.16.0)
Requires-Dist: Eve (>=0.9.0)
Requires-Dist: exrex (>=0.10.5)
Requires-Dist: Faker (>=2.0.0)
Requires-Dist: flasgger (>=0.9.0)
Requires-Dist: Flask (>=1.1.0)
Requires-Dist: Jinja2 (>=2.10)
Requires-Dist: jsonschema (<3.0.0,>=2.6.0)
Requires-Dist: pandas (>=0.25.0)
Requires-Dist: py-healthcheck (>=1.9.0)
Requires-Dist: simplejson (>=3.16.0)
Provides-Extra: release
Requires-Dist: bumpversion (>=0.5.0) ; extra == 'release'
Requires-Dist: gunicorn (>=19.9.0) ; extra == 'release'
Requires-Dist: Sphinx (>=2.2.0) ; extra == 'release'
Requires-Dist: sphinx-rtd-theme (>=0.4.0) ; extra == 'release'
